LICENSE
README.md
setup.py
maixcdk.egg-info/PKG-INFO
maixcdk.egg-info/SOURCES.txt
maixcdk.egg-info/dependency_links.txt
maixcdk.egg-info/entry_points.txt
maixcdk.egg-info/requires.txt
maixcdk.egg-info/top_level.txt
maixtool/__init__.py
maixtool/__main__.py
maixtool/app_deploy.py
maixtool/app_release.py
maixtool/maixcdk.py
maixtool/maixtool.py
maixtool/version.py