Metadata-Version: 2.1
Name: maixcdk
Version: 1.0.0
Summary: Tools for Maix series development
Home-page: https://github.com/Sipeed/MaixCDK
Author: Sipeed
Author-email: support@sipeed.com
License: Apache 2.0
Keywords: Maix MaixCDK MaixPy maixtool
Platform: UNKNOWN
Classifier: Development Status :: 5 - Production/Stable
Classifier: Intended Audience :: Developers
Classifier: Intended Audience :: Education
Classifier: Intended Audience :: Science/Research
Classifier: Topic :: Software Development :: Embedded Systems
Classifier: License :: OSI Approved :: Apache Software License
Classifier: Programming Language :: Python :: 3
License-File: LICENSE
